meeracv/__init__.py
meeracv-0.2.2.dist-info/LICENSE
meeracv-0.2.2.dist-info/METADATA
meeracv-0.2.2.dist-info/WHEEL
meeracv-0.2.2.dist-info/top_level.txt
meeracv-0.2.2.dist-info/RECORD
