Metadata-Version: 2.1
Name: meeracv
Version: 0.2.2
Summary: A computer vision library inspired by OpenCV
Home-page: https://github.com/KashyapSinh-Gohil/meeracv
Author: Kashyapsinh Gohil
Author-email: k.agohil000@gmail.com
License: MIT
Platform: UNKNOWN
Classifier: Programming Language :: Python :: 3
Classifier: License :: OSI Approved :: MIT License
Classifier: Operating System :: OS Independent
Requires-Python: >=3.7
Requires-Dist: numpy >=1.19.0
Requires-Dist: pillow >=8.0.0
Requires-Dist: scipy >=1.6.0
Requires-Dist: opencv-python-headless >=4.5.0
Requires-Dist: face-recognition >=1.3.0
Requires-Dist: pytesseract >=0.3.8
Requires-Dist: mediapipe >=0.8.0
Requires-Dist: scikit-learn >=0.24.0
